solis/__init__.py
solis/cli.py
solis/exceptions.py
solis/solis.py
solis/utils.py
solis-0.1.1.dist-info/METADATA
solis-0.1.1.dist-info/WHEEL
solis-0.1.1.dist-info/entry_points.txt
solis-0.1.1.dist-info/RECORD
