Metadata-Version: 2.1
Name: solis
Version: 0.1.1
Summary: A tool to control Solis Hybrid Inverters
License: MIT
Author: Dan Foster
Author-email: dan@zem.org.uk
Requires-Python: >=3.8,<4.0
Classifier: License :: OSI Approved :: MIT License
Classifier: Programming Language :: Python :: 3
Classifier: Programming Language :: Python :: 3.8
Classifier: Programming Language :: Python :: 3.9
Classifier: Programming Language :: Python :: 3.10
Classifier: Programming Language :: Python :: 3.11
Requires-Dist: asyncclick (>=8.1.3.4,<9.0.0.0)
Requires-Dist: click (>=8.1.3,<9.0.0)
Requires-Dist: zem-pysolarmanv5 (>=2.5.0rc2,<3.0.0)
